{
    ".EVOL7D": {
        "asks": [],
        "bids": []
    },
    ".TRXXBT": {
        "asks": [],
        "bids": []
    },
    ".TRXXBT30M": {
        "asks": [],
        "bids": []
    },
    ".BADAXBT": {
        "asks": [],
        "bids": []
    },
    ".BADAXBT30M": {
        "asks": [],
        "bids": []
    },
    ".BBCHXBT": {
        "asks": [],
        "bids": []
    },
    ".BBCHXBT30M": {
        "asks": [],
        "bids": []
    },
    ".BEOSXBT": {
        "asks": [],
        "bids": []
    },
    ".BEOSXBT30M": {
        "asks": [],
        "bids": []
    },
    ".BXRPXBT": {
        "asks": [],
        "bids": []
    },
    ".BXRPXBT30M": {
        "asks": [],
        "bids": []
    },
    "XRPH19": {
        "asks": [
            [
                8.256e-05,
                590512
            ],
            [
                8.257e-05,
                16490
            ],
            [
                8.258e-05,
                225149
            ],
            [
                8.259e-05,
                1000
            ],
            [
                8.26e-05,
                7148
            ],
            [
                8.261e-05,
                132
            ],
            [
                8.262e-05,
                130310
            ],
            [
                8.263e-05,
                25959
            ],
            [
                8.264e-05,
                32499
            ],
            [
                8.265e-05,
                131608
            ],
            [
                8.268e-05,
                4002
            ],
            [
                8.269e-05,
                75096
            ],
            [
                8.27e-05,
                8100
            ],
            [
                8.272e-05,
                19111
            ],
            [
                8.273e-05,
                31831
            ],
            [
                8.274e-05,
                1229
            ],
            [
                8.275e-05,
                36100
            ],
            [
                8.276e-05,
                2000
            ],
            [
                8.277e-05,
                82681
            ],
            [
                8.278e-05,
                1100
            ],
            [
                8.279e-05,
                19643
            ],
            [
                8.28e-05,
                45321
            ],
            [
                8.281e-05,
                32050
            ],
            [
                8.282e-05,
                1000
            ],
            [
                8.283e-05,
                17605
            ]
        ],
        "bids": [
            [
                8.255e-05,
                179121
            ],
            [
                8.254e-05,
                532
            ],
            [
                8.252e-05,
                564
            ],
            [
                8.251e-05,
                28043
            ],
            [
                8.25e-05,
                12096
            ],
            [
                8.248e-05,
                1128
            ],
            [
                8.247e-05,
                1401
            ],
            [
                8.246e-05,
                1000
            ],
            [
                8.245e-05,
                1401
            ],
            [
                8.241e-05,
                68000
            ],
            [
                8.24e-05,
                55000
            ],
            [
                8.239e-05,
                8000
            ],
            [
                8.237e-05,
                75
            ],
            [
                8.235e-05,
                15000
            ],
            [
                8.234e-05,
                15000
            ],
            [
                8.233e-05,
                8220
            ],
            [
                8.232e-05,
                3066
            ],
            [
                8.231e-05,
                15392
            ],
            [
                8.23e-05,
                38229
            ],
            [
                8.229e-05,
                500
            ],
            [
                8.228e-05,
                4237
            ],
            [
                8.227e-05,
                40000
            ],
            [
                8.226e-05,
                6300
            ],
            [
                8.225e-05,
                37000
            ],
            [
                8.224e-05,
                5031
            ]
        ]
    },
    "BCHH19": {
        "asks": [
            [
                0.0345,
                167
            ],
            [
                0.0346,
                1636
            ],
            [
                0.0347,
                659
            ],
            [
                0.0348,
                542
            ],
            [
                0.0349,
                1075
            ],
            [
                0.035,
                313
            ],
            [
                0.0351,
                791
            ],
            [
                0.0352,
                1082
            ],
            [
                0.0353,
                518
            ],
            [
                0.0354,
                515
            ],
            [
                0.0355,
                843
            ],
            [
                0.0356,
                2690
            ],
            [
                0.0357,
                309
            ],
            [
                0.0358,
                253
            ],
            [
                0.0359,
                492
            ],
            [
                0.036,
                459
            ],
            [
                0.0361,
                372
            ],
            [
                0.0362,
                422
            ],
            [
                0.0363,
                290
            ],
            [
                0.0364,
                57
            ],
            [
                0.0365,
                114
            ],
            [
                0.0366,
                253
            ],
            [
                0.0367,
                68
            ],
            [
                0.0368,
                423
            ],
            [
                0.0369,
                218
            ]
        ],
        "bids": [
            [
                0.0344,
                1055
            ],
            [
                0.0343,
                1044
            ],
            [
                0.0342,
                1388
            ],
            [
                0.0341,
                638
            ],
            [
                0.034,
                522
            ],
            [
                0.0339,
                333
            ],
            [
                0.0338,
                459
            ],
            [
                0.0337,
                638
            ],
            [
                0.0336,
                1212
            ],
            [
                0.0335,
                407
            ],
            [
                0.0334,
                1465
            ],
            [
                0.0333,
                826
            ],
            [
                0.0332,
                1939
            ],
            [
                0.0331,
                369
            ],
            [
                0.033,
                676
            ],
            [
                0.0329,
                127
            ],
            [
                0.0328,
                261
            ],
            [
                0.0327,
                437
            ],
            [
                0.0326,
                190
            ],
            [
                0.0325,
                2196
            ],
            [
                0.0324,
                9
            ],
            [
                0.0323,
                694
            ],
            [
                0.0322,
                287
            ],
            [
                0.0321,
                1112
            ],
            [
                0.032,
                794
            ]
        ]
    },
    "ADAH19": {
        "asks": [
            [
                1.117e-05,
                141554
            ],
            [
                1.118e-05,
                46100
            ],
            [
                1.119e-05,
                460989
            ],
            [
                1.12e-05,
                742519
            ],
            [
                1.121e-05,
                742896
            ],
            [
                1.122e-05,
                557959
            ],
            [
                1.123e-05,
                1296805
            ],
            [
                1.124e-05,
                429176
            ],
            [
                1.125e-05,
                338025
            ],
            [
                1.126e-05,
                310316
            ],
            [
                1.127e-05,
                799918
            ],
            [
                1.128e-05,
                359118
            ],
            [
                1.129e-05,
                95145
            ],
            [
                1.13e-05,
                503268
            ],
            [
                1.131e-05,
                573769
            ],
            [
                1.132e-05,
                321300
            ],
            [
                1.133e-05,
                330786
            ],
            [
                1.134e-05,
                304263
            ],
            [
                1.135e-05,
                334990
            ],
            [
                1.136e-05,
                922900
            ],
            [
                1.137e-05,
                620504
            ],
            [
                1.138e-05,
                546481
            ],
            [
                1.139e-05,
                1137180
            ],
            [
                1.14e-05,
                624923
            ],
            [
                1.141e-05,
                279348
            ]
        ],
        "bids": [
            [
                1.116e-05,
                816162
            ],
            [
                1.115e-05,
                190807
            ],
            [
                1.114e-05,
                406958
            ],
            [
                1.113e-05,
                237436
            ],
            [
                1.112e-05,
                278605
            ],
            [
                1.111e-05,
                342865
            ],
            [
                1.11e-05,
                337673
            ],
            [
                1.109e-05,
                84068
            ],
            [
                1.108e-05,
                1365429
            ],
            [
                1.107e-05,
                137626
            ],
            [
                1.106e-05,
                284252
            ],
            [
                1.105e-05,
                95909
            ],
            [
                1.104e-05,
                532523
            ],
            [
                1.103e-05,
                117240
            ],
            [
                1.102e-05,
                7695
            ],
            [
                1.101e-05,
                171372
            ],
            [
                1.1e-05,
                241563
            ],
            [
                1.099e-05,
                285156
            ],
            [
                1.098e-05,
                99500
            ],
            [
                1.097e-05,
                357530
            ],
            [
                1.096e-05,
                149611
            ],
            [
                1.095e-05,
                286398
            ],
            [
                1.094e-05,
                1137364
            ],
            [
                1.093e-05,
                666387
            ],
            [
                1.092e-05,
                364503
            ]
        ]
    },
    "EOSH19": {
        "asks": [
            [
                0.0009612,
                3703
            ],
            [
                0.0009613,
                110
            ],
            [
                0.0009614,
                25
            ],
            [
                0.0009615,
                200
            ],
            [
                0.0009619,
                264
            ],
            [
                0.000962,
                100
            ],
            [
                0.0009621,
                5
            ],
            [
                0.0009622,
                62
            ],
            [
                0.0009623,
                400
            ],
            [
                0.0009626,
                77
            ],
            [
                0.0009627,
                100
            ],
            [
                0.000963,
                681
            ],
            [
                0.0009634,
                1769
            ],
            [
                0.0009635,
                145
            ],
            [
                0.0009636,
                300
            ],
            [
                0.0009637,
                800
            ],
            [
                0.0009639,
                2089
            ],
            [
                0.000964,
                1623
            ],
            [
                0.0009645,
                1000
            ],
            [
                0.0009646,
                3018
            ],
            [
                0.0009647,
                3000
            ],
            [
                0.0009649,
                1906
            ],
            [
                0.0009652,
                2269
            ],
            [
                0.0009653,
                5
            ],
            [
                0.000966,
                10
            ]
        ],
        "bids": [
            [
                0.0009611,
                20864
            ],
            [
                0.000961,
                19
            ],
            [
                0.0009609,
                2800
            ],
            [
                0.0009608,
                3272
            ],
            [
                0.0009605,
                17000
            ],
            [
                0.0009604,
                1063
            ],
            [
                0.0009603,
                400
            ],
            [
                0.0009602,
                80
            ],
            [
                0.00096,
                2976
            ],
            [
                0.0009599,
                66
            ],
            [
                0.0009597,
                5
            ],
            [
                0.0009596,
                625
            ],
            [
                0.0009595,
                80
            ],
            [
                0.0009594,
                463
            ],
            [
                0.0009593,
                160
            ],
            [
                0.0009592,
                1581
            ],
            [
                0.0009591,
                19
            ],
            [
                0.000959,
                154
            ],
            [
                0.0009589,
                1451
            ],
            [
                0.0009588,
                1000
            ],
            [
                0.0009586,
                1492
            ],
            [
                0.0009585,
                1000
            ],
            [
                0.0009583,
                2000
            ],
            [
                0.0009581,
                120
            ],
            [
                0.0009576,
                5
            ]
        ]
    },
    "TRXH19": {
        "asks": [
            [
                6.15e-06,
                659078
            ],
            [
                6.16e-06,
                1576721
            ],
            [
                6.17e-06,
                2923092
            ],
            [
                6.18e-06,
                925751
            ],
            [
                6.19e-06,
                2578696
            ],
            [
                6.2e-06,
                1141919
            ],
            [
                6.21e-06,
                556083
            ],
            [
                6.22e-06,
                1568252
            ],
            [
                6.23e-06,
                2236084
            ],
            [
                6.24e-06,
                539290
            ],
            [
                6.25e-06,
                3018417
            ],
            [
                6.26e-06,
                809473
            ],
            [
                6.27e-06,
                1512960
            ],
            [
                6.28e-06,
                1866125
            ],
            [
                6.29e-06,
                989604
            ],
            [
                6.3e-06,
                2833460
            ],
            [
                6.31e-06,
                1499153
            ],
            [
                6.32e-06,
                829613
            ],
            [
                6.33e-06,
                3713697
            ],
            [
                6.34e-06,
                1476662
            ],
            [
                6.35e-06,
                1077821
            ],
            [
                6.36e-06,
                1321519
            ],
            [
                6.37e-06,
                1051100
            ],
            [
                6.38e-06,
                1569298
            ],
            [
                6.39e-06,
                805349
            ]
        ],
        "bids": [
            [
                6.14e-06,
                3227953
            ],
            [
                6.13e-06,
                2152314
            ],
            [
                6.12e-06,
                1844734
            ],
            [
                6.11e-06,
                585388
            ],
            [
                6.1e-06,
                474976
            ],
            [
                6.09e-06,
                481877
            ],
            [
                6.08e-06,
                3310274
            ],
            [
                6.07e-06,
                817621
            ],
            [
                6.06e-06,
                813048
            ],
            [
                6.05e-06,
                921259
            ],
            [
                6.04e-06,
                1023409
            ],
            [
                6.03e-06,
                1093825
            ],
            [
                6.02e-06,
                1063633
            ],
            [
                6.01e-06,
                1184640
            ],
            [
                6e-06,
                2697796
            ],
            [
                5.99e-06,
                900621
            ],
            [
                5.98e-06,
                755028
            ],
            [
                5.97e-06,
                542665
            ],
            [
                5.96e-06,
                943388
            ],
            [
                5.95e-06,
                439844
            ],
            [
                5.94e-06,
                305685
            ],
            [
                5.93e-06,
                143976
            ],
            [
                5.92e-06,
                2607543
            ],
            [
                5.91e-06,
                1434612
            ],
            [
                5.9e-06,
                1011186
            ]
        ]
    },
    ".XBT": {
        "asks": [],
        "bids": []
    },
    ".XBT30M": {
        "asks": [],
        "bids": []
    },
    ".XBTBON": {
        "asks": [],
        "bids": []
    },
    ".XBTBON8H": {
        "asks": [],
        "bids": []
    },
    ".XBTUSDPI": {
        "asks": [],
        "bids": []
    },
    ".XBTUSDPI8H": {
        "asks": [],
        "bids": []
    },
    ".XBTBON2H": {
        "asks": [],
        "bids": []
    },
    ".XBTUSDPI2H": {
        "asks": [],
        "bids": []
    },
    ".BXBT": {
        "asks": [],
        "bids": []
    },
    ".BXBT30M": {
        "asks": [],
        "bids": []
    },
    ".XBTJPY": {
        "asks": [],
        "bids": []
    },
    ".XBTJPY30M": {
        "asks": [],
        "bids": []
    },
    ".BXBTJPY": {
        "asks": [],
        "bids": []
    },
    ".BXBTJPY30M": {
        "asks": [],
        "bids": []
    },
    ".BVOL": {
        "asks": [],
        "bids": []
    },
    ".BVOL24H": {
        "asks": [],
        "bids": []
    },
    ".BVOL7D": {
        "asks": [],
        "bids": []
    },
    ".ETHBON": {
        "asks": [],
        "bids": []
    },
    ".ETHBON2H": {
        "asks": [],
        "bids": []
    },
    ".ETHBON8H": {
        "asks": [],
        "bids": []
    },
    ".ETHUSDPI": {
        "asks": [],
        "bids": []
    },
    ".ETHUSDPI2H": {
        "asks": [],
        "bids": []
    },
    ".ETHUSDPI8H": {
        "asks": [],
        "bids": []
    },
    ".BETH": {
        "asks": [],
        "bids": []
    },
    ".BETH30M": {
        "asks": [],
        "bids": []
    },
    ".BETHXBT": {
        "asks": [],
        "bids": []
    },
    ".BETHXBT30M": {
        "asks": [],
        "bids": []
    },
    ".BLTCXBT": {
        "asks": [],
        "bids": []
    },
    ".BLTCXBT30M": {
        "asks": [],
        "bids": []
    },
    ".USDBON": {
        "asks": [],
        "bids": []
    },
    ".USDBON8H": {
        "asks": [],
        "bids": []
    },
    ".USDBON2H": {
        "asks": [],
        "bids": []
    },
    "BTC/USD": {
        "asks": [
            [
                3854,
                710638
            ],
            [
                3854.5,
                195978
            ],
            [
                3855,
                21645
            ],
            [
                3855.5,
                14095
            ],
            [
                3856,
                47085
            ],
            [
                3856.5,
                245624
            ],
            [
                3857,
                341311
            ],
            [
                3857.5,
                129221
            ],
            [
                3858,
                224018
            ],
            [
                3858.5,
                121410
            ],
            [
                3859,
                173005
            ],
            [
                3859.5,
                46334
            ],
            [
                3860,
                265096
            ],
            [
                3860.5,
                59846
            ],
            [
                3861,
                19165
            ],
            [
                3861.5,
                66488
            ],
            [
                3862,
                19130
            ],
            [
                3862.5,
                41743
            ],
            [
                3863,
                67795
            ],
            [
                3863.5,
                31686
            ],
            [
                3864,
                197288
            ],
            [
                3864.5,
                171256
            ],
            [
                3865,
                227825
            ],
            [
                3865.5,
                42941
            ],
            [
                3866,
                52210
            ]
        ],
        "bids": [
            [
                3853.5,
                846191
            ],
            [
                3853,
                424603
            ],
            [
                3852.5,
                80065
            ],
            [
                3852,
                18782
            ],
            [
                3851.5,
                50451
            ],
            [
                3851,
                23949
            ],
            [
                3850.5,
                146684
            ],
            [
                3850,
                237736
            ],
            [
                3849.5,
                406713
            ],
            [
                3849,
                170344
            ],
            [
                3848.5,
                336670
            ],
            [
                3848,
                110670
            ],
            [
                3847.5,
                403929
            ],
            [
                3847,
                580205
            ],
            [
                3846.5,
                291837
            ],
            [
                3846,
                237861
            ],
            [
                3845.5,
                364930
            ],
            [
                3845,
                981514
            ],
            [
                3844.5,
                64723
            ],
            [
                3844,
                345486
            ],
            [
                3843.5,
                279143
            ],
            [
                3843,
                240430
            ],
            [
                3842.5,
                154693
            ],
            [
                3842,
                177429
            ],
            [
                3841.5,
                395838
            ]
        ]
    },
    "XBT7D_U105": {
        "asks": [
            [
                0.00336,
                18
            ],
            [
                0.00361,
                55
            ],
            [
                0.00386,
                78
            ],
            [
                0.00388,
                1
            ],
            [
                0.004,
                1
            ],
            [
                0.00411,
                102
            ],
            [
                0.00436,
                125
            ],
            [
                0.0045,
                2
            ],
            [
                0.0056,
                1
            ],
            [
                0.006,
                1
            ],
            [
                0.0072,
                1
            ]
        ],
        "bids": [
            [
                0.00285,
                13
            ],
            [
                0.0026,
                8
            ],
            [
                0.00235,
                14
            ],
            [
                0.0023,
                1
            ],
            [
                0.0021,
                38
            ],
            [
                0.00185,
                61
            ],
            [
                9e-05,
                5
            ],
            [
                1e-05,
                110
            ]
        ]
    },
    "XBT7D_D95": {
        "asks": [
            [
                0.00144,
                13
            ],
            [
                0.00169,
                45
            ],
            [
                0.00194,
                68
            ],
            [
                0.00219,
                91
            ],
            [
                0.00244,
                115
            ]
        ],
        "bids": [
            [
                0.00094,
                1
            ],
            [
                0.00093,
                7
            ],
            [
                0.00068,
                1
            ],
            [
                0.00043,
                25
            ],
            [
                0.0003,
                5
            ],
            [
                0.00025,
                10
            ],
            [
                0.00018,
                48
            ],
            [
                5e-05,
                100
            ],
            [
                2e-05,
                10
            ],
            [
                1e-05,
                161
            ]
        ]
    },
    "XBTH19": {
        "asks": [
            [
                3849.5,
                62211
            ],
            [
                3850,
                3015
            ],
            [
                3850.5,
                16900
            ],
            [
                3851,
                5600
            ],
            [
                3851.5,
                5000
            ],
            [
                3852,
                1000
            ],
            [
                3852.5,
                10000
            ],
            [
                3853,
                4426
            ],
            [
                3853.5,
                6635
            ],
            [
                3854,
                63654
            ],
            [
                3855,
                4000
            ],
            [
                3855.5,
                385550
            ],
            [
                3856,
                3346
            ],
            [
                3856.5,
                20001
            ],
            [
                3857.5,
                10000
            ],
            [
                3858,
                20000
            ],
            [
                3858.5,
                41500
            ],
            [
                3859,
                2385
            ],
            [
                3859.5,
                1083
            ],
            [
                3860,
                29100
            ],
            [
                3860.5,
                3975
            ],
            [
                3861,
                48022
            ],
            [
                3861.5,
                15853
            ],
            [
                3862,
                30500
            ],
            [
                3862.5,
                50
            ]
        ],
        "bids": [
            [
                3849,
                55089
            ],
            [
                3848.5,
                50025
            ],
            [
                3848,
                71610
            ],
            [
                3847.5,
                5015
            ],
            [
                3847,
                11000
            ],
            [
                3846.5,
                49999
            ],
            [
                3846,
                26723
            ],
            [
                3845.5,
                50017
            ],
            [
                3845,
                29031
            ],
            [
                3844.5,
                41179
            ],
            [
                3844,
                100
            ],
            [
                3843.5,
                6550
            ],
            [
                3843,
                36440
            ],
            [
                3842.5,
                36535
            ],
            [
                3842,
                1250
            ],
            [
                3841.5,
                27200
            ],
            [
                3841,
                3000
            ],
            [
                3840,
                13836
            ],
            [
                3839.5,
                7650
            ],
            [
                3839,
                3100
            ],
            [
                3838.5,
                4000
            ],
            [
                3838,
                11915
            ],
            [
                3837.5,
                22000
            ],
            [
                3837,
                32516
            ],
            [
                3836.5,
                38617
            ]
        ]
    },
    "XBTM19": {
        "asks": [
            [
                3832.5,
                82334
            ],
            [
                3833.5,
                1953
            ],
            [
                3834.5,
                215
            ],
            [
                3835,
                100
            ],
            [
                3835.5,
                4791
            ],
            [
                3836,
                5000
            ],
            [
                3836.5,
                58191
            ],
            [
                3837,
                4896
            ],
            [
                3837.5,
                605
            ],
            [
                3838.5,
                14824
            ],
            [
                3839,
                10
            ],
            [
                3839.5,
                18870
            ],
            [
                3840,
                47135
            ],
            [
                3840.5,
                4033
            ],
            [
                3841.5,
                234
            ],
            [
                3842,
                10020
            ],
            [
                3842.5,
                5000
            ],
            [
                3843,
                9000
            ],
            [
                3844,
                4000
            ],
            [
                3844.5,
                90
            ],
            [
                3845,
                26572
            ],
            [
                3845.5,
                100
            ],
            [
                3846,
                130
            ],
            [
                3846.5,
                3100
            ],
            [
                3847,
                10100
            ]
        ],
        "bids": [
            [
                3832,
                15891
            ],
            [
                3831.5,
                5000
            ],
            [
                3831,
                13418
            ],
            [
                3830.5,
                10891
            ],
            [
                3830,
                4500
            ],
            [
                3828.5,
                11064
            ],
            [
                3828,
                17000
            ],
            [
                3827,
                3720
            ],
            [
                3826.5,
                4792
            ],
            [
                3826,
                17007
            ],
            [
                3825.5,
                3081
            ],
            [
                3825,
                5725
            ],
            [
                3824.5,
                30
            ],
            [
                3824,
                723
            ],
            [
                3823.5,
                1820
            ],
            [
                3823,
                4528
            ],
            [
                3822.5,
                13972
            ],
            [
                3822,
                63654
            ],
            [
                3821.5,
                3938
            ],
            [
                3821,
                9256
            ],
            [
                3820.5,
                2815
            ],
            [
                3820,
                27435
            ],
            [
                3819.5,
                12809
            ],
            [
                3819,
                6000
            ],
            [
                3818.5,
                200
            ]
        ]
    },
    "ETH/USD": {
        "asks": [
            [
                136.65,
                644481
            ],
            [
                136.7,
                451615
            ],
            [
                136.75,
                392883
            ],
            [
                136.8,
                119777
            ],
            [
                136.85,
                89820
            ],
            [
                136.9,
                152181
            ],
            [
                136.95,
                502282
            ],
            [
                137,
                275279
            ],
            [
                137.05,
                35837
            ],
            [
                137.1,
                36282
            ],
            [
                137.15,
                41054
            ],
            [
                137.2,
                234873
            ],
            [
                137.25,
                102582
            ],
            [
                137.3,
                97302
            ],
            [
                137.35,
                69407
            ],
            [
                137.4,
                67076
            ],
            [
                137.45,
                23846
            ],
            [
                137.5,
                324157
            ],
            [
                137.55,
                10200
            ],
            [
                137.6,
                116956
            ],
            [
                137.65,
                380097
            ],
            [
                137.7,
                73289
            ],
            [
                137.75,
                398172
            ],
            [
                137.8,
                51306
            ],
            [
                137.85,
                21310
            ]
        ],
        "bids": [
            [
                136.6,
                55418
            ],
            [
                136.55,
                3360
            ],
            [
                136.5,
                200013
            ],
            [
                136.45,
                141704
            ],
            [
                136.4,
                140842
            ],
            [
                136.35,
                358783
            ],
            [
                136.3,
                177871
            ],
            [
                136.25,
                397307
            ],
            [
                136.2,
                25268
            ],
            [
                136.15,
                94881
            ],
            [
                136.1,
                212387
            ],
            [
                136.05,
                262025
            ],
            [
                136,
                873989
            ],
            [
                135.95,
                74147
            ],
            [
                135.9,
                39959
            ],
            [
                135.85,
                191840
            ],
            [
                135.8,
                321989
            ],
            [
                135.75,
                180133
            ],
            [
                135.7,
                281536
            ],
            [
                135.65,
                137255
            ],
            [
                135.6,
                27330
            ],
            [
                135.55,
                289781
            ],
            [
                135.5,
                566404
            ],
            [
                135.45,
                68872
            ],
            [
                135.4,
                383876
            ]
        ]
    },
    "ETHH19": {
        "asks": [
            [
                0.03544,
                39
            ],
            [
                0.03545,
                10
            ],
            [
                0.03547,
                32
            ],
            [
                0.03549,
                55
            ],
            [
                0.0355,
                160
            ],
            [
                0.03551,
                158
            ],
            [
                0.03552,
                76
            ],
            [
                0.03554,
                426
            ],
            [
                0.03555,
                81
            ],
            [
                0.03556,
                20
            ],
            [
                0.03557,
                125
            ],
            [
                0.03559,
                10
            ],
            [
                0.0356,
                1
            ],
            [
                0.03561,
                3
            ],
            [
                0.03562,
                7
            ],
            [
                0.03563,
                77
            ],
            [
                0.03564,
                5
            ],
            [
                0.03565,
                4
            ],
            [
                0.03566,
                52
            ],
            [
                0.03567,
                4
            ],
            [
                0.03568,
                51
            ],
            [
                0.0357,
                59
            ],
            [
                0.03571,
                800
            ],
            [
                0.03572,
                3
            ],
            [
                0.03573,
                16
            ]
        ],
        "bids": [
            [
                0.03543,
                509
            ],
            [
                0.03542,
                192
            ],
            [
                0.03541,
                40
            ],
            [
                0.0354,
                49
            ],
            [
                0.03539,
                232
            ],
            [
                0.03538,
                44
            ],
            [
                0.03537,
                114
            ],
            [
                0.03536,
                24
            ],
            [
                0.03535,
                102
            ],
            [
                0.03534,
                415
            ],
            [
                0.03533,
                6
            ],
            [
                0.03532,
                1
            ],
            [
                0.03531,
                99
            ],
            [
                0.0353,
                44
            ],
            [
                0.03529,
                50
            ],
            [
                0.03528,
                436
            ],
            [
                0.03527,
                1
            ],
            [
                0.03525,
                34
            ],
            [
                0.03524,
                5
            ],
            [
                0.03523,
                65
            ],
            [
                0.03521,
                2
            ],
            [
                0.0352,
                13
            ],
            [
                0.03519,
                844
            ],
            [
                0.03518,
                46
            ],
            [
                0.03516,
                63
            ]
        ]
    },
    "LTCH19": {
        "asks": [
            [
                0.01366,
                844
            ],
            [
                0.01367,
                323
            ],
            [
                0.01368,
                203
            ],
            [
                0.01369,
                87
            ],
            [
                0.0137,
                531
            ],
            [
                0.01371,
                423
            ],
            [
                0.01372,
                2133
            ],
            [
                0.01373,
                22
            ],
            [
                0.01374,
                190
            ],
            [
                0.01375,
                1059
            ],
            [
                0.01376,
                49
            ],
            [
                0.01377,
                127
            ],
            [
                0.01378,
                774
            ],
            [
                0.01379,
                341
            ],
            [
                0.0138,
                1543
            ],
            [
                0.01381,
                2230
            ],
            [
                0.01382,
                3157
            ],
            [
                0.01383,
                280
            ],
            [
                0.01384,
                135
            ],
            [
                0.01385,
                1128
            ],
            [
                0.01386,
                340
            ],
            [
                0.01387,
                428
            ],
            [
                0.01388,
                6304
            ],
            [
                0.01389,
                211
            ],
            [
                0.0139,
                687
            ]
        ],
        "bids": [
            [
                0.01365,
                752
            ],
            [
                0.01364,
                665
            ],
            [
                0.01363,
                1254
            ],
            [
                0.01362,
                177
            ],
            [
                0.01361,
                783
            ],
            [
                0.0136,
                829
            ],
            [
                0.01359,
                916
            ],
            [
                0.01358,
                2239
            ],
            [
                0.01357,
                991
            ],
            [
                0.01356,
                1114
            ],
            [
                0.01355,
                618
            ],
            [
                0.01354,
                5207
            ],
            [
                0.01353,
                946
            ],
            [
                0.01352,
                354
            ],
            [
                0.01351,
                2215
            ],
            [
                0.0135,
                2237
            ],
            [
                0.01349,
                209
            ],
            [
                0.01348,
                449
            ],
            [
                0.01347,
                73
            ],
            [
                0.01346,
                76
            ],
            [
                0.01345,
                246
            ],
            [
                0.01344,
                59
            ],
            [
                0.01343,
                203
            ],
            [
                0.01342,
                664
            ],
            [
                0.01341,
                930
            ]
        ]
    }
}