{
    ".EVOL7D": {
        "asks": [],
        "bids": []
    },
    ".TRXXBT": {
        "asks": [],
        "bids": []
    },
    ".TRXXBT30M": {
        "asks": [],
        "bids": []
    },
    ".BADAXBT": {
        "asks": [],
        "bids": []
    },
    ".BADAXBT30M": {
        "asks": [],
        "bids": []
    },
    ".BBCHXBT": {
        "asks": [],
        "bids": []
    },
    ".BBCHXBT30M": {
        "asks": [],
        "bids": []
    },
    ".BEOSXBT": {
        "asks": [],
        "bids": []
    },
    ".BEOSXBT30M": {
        "asks": [],
        "bids": []
    },
    ".BXRPXBT": {
        "asks": [],
        "bids": []
    },
    ".BXRPXBT30M": {
        "asks": [],
        "bids": []
    },
    "XRPH19": {
        "asks": [
            [
                8.174e-05,
                149855
            ],
            [
                8.175e-05,
                85000
            ],
            [
                8.176e-05,
                11419
            ],
            [
                8.177e-05,
                2518
            ],
            [
                8.178e-05,
                14000
            ],
            [
                8.179e-05,
                16066
            ],
            [
                8.181e-05,
                1199
            ],
            [
                8.182e-05,
                4001
            ],
            [
                8.183e-05,
                132
            ],
            [
                8.184e-05,
                13459
            ],
            [
                8.185e-05,
                1100
            ],
            [
                8.186e-05,
                16000
            ],
            [
                8.187e-05,
                20002
            ],
            [
                8.19e-05,
                5000
            ],
            [
                8.192e-05,
                20000
            ],
            [
                8.193e-05,
                85523
            ],
            [
                8.194e-05,
                20000
            ],
            [
                8.195e-05,
                25800
            ],
            [
                8.197e-05,
                1500
            ],
            [
                8.199e-05,
                23901
            ],
            [
                8.2e-05,
                201900
            ],
            [
                8.201e-05,
                61
            ],
            [
                8.202e-05,
                24054
            ],
            [
                8.203e-05,
                235376
            ],
            [
                8.204e-05,
                279210
            ]
        ],
        "bids": [
            [
                8.173e-05,
                314941
            ],
            [
                8.172e-05,
                14118
            ],
            [
                8.171e-05,
                11062
            ],
            [
                8.17e-05,
                8466
            ],
            [
                8.169e-05,
                3118
            ],
            [
                8.168e-05,
                786
            ],
            [
                8.167e-05,
                10245
            ],
            [
                8.166e-05,
                22750
            ],
            [
                8.165e-05,
                21470
            ],
            [
                8.164e-05,
                26873
            ],
            [
                8.163e-05,
                29066
            ],
            [
                8.162e-05,
                110199
            ],
            [
                8.161e-05,
                150721
            ],
            [
                8.16e-05,
                38219
            ],
            [
                8.159e-05,
                53335
            ],
            [
                8.158e-05,
                13959
            ],
            [
                8.156e-05,
                69638
            ],
            [
                8.155e-05,
                10739
            ],
            [
                8.154e-05,
                1350
            ],
            [
                8.153e-05,
                1710
            ],
            [
                8.152e-05,
                9000
            ],
            [
                8.151e-05,
                27533
            ],
            [
                8.15e-05,
                87756
            ],
            [
                8.149e-05,
                19188
            ],
            [
                8.148e-05,
                32200
            ]
        ]
    },
    "BCHH19": {
        "asks": [
            [
                0.0345,
                1130
            ],
            [
                0.0346,
                1493
            ],
            [
                0.0347,
                708
            ],
            [
                0.0348,
                1075
            ],
            [
                0.0349,
                1007
            ],
            [
                0.035,
                486
            ],
            [
                0.0351,
                1694
            ],
            [
                0.0352,
                388
            ],
            [
                0.0353,
                1011
            ],
            [
                0.0354,
                490
            ],
            [
                0.0355,
                786
            ],
            [
                0.0356,
                831
            ],
            [
                0.0357,
                685
            ],
            [
                0.0358,
                1200
            ],
            [
                0.0359,
                1477
            ],
            [
                0.036,
                2346
            ],
            [
                0.0361,
                957
            ],
            [
                0.0362,
                280
            ],
            [
                0.0363,
                123
            ],
            [
                0.0364,
                452
            ],
            [
                0.0365,
                706
            ],
            [
                0.0366,
                109
            ],
            [
                0.0367,
                217
            ],
            [
                0.0368,
                251
            ],
            [
                0.0369,
                441
            ]
        ],
        "bids": [
            [
                0.0344,
                158
            ],
            [
                0.0343,
                655
            ],
            [
                0.0342,
                741
            ],
            [
                0.0341,
                2091
            ],
            [
                0.034,
                1555
            ],
            [
                0.0339,
                766
            ],
            [
                0.0338,
                143
            ],
            [
                0.0337,
                475
            ],
            [
                0.0336,
                953
            ],
            [
                0.0335,
                327
            ],
            [
                0.0334,
                549
            ],
            [
                0.0333,
                763
            ],
            [
                0.0332,
                1186
            ],
            [
                0.0331,
                834
            ],
            [
                0.033,
                358
            ],
            [
                0.0329,
                3020
            ],
            [
                0.0328,
                371
            ],
            [
                0.0327,
                412
            ],
            [
                0.0326,
                1080
            ],
            [
                0.0325,
                611
            ],
            [
                0.0324,
                513
            ],
            [
                0.0323,
                1228
            ],
            [
                0.0322,
                518
            ],
            [
                0.0321,
                1618
            ],
            [
                0.032,
                1008
            ]
        ]
    },
    "ADAH19": {
        "asks": [
            [
                1.115e-05,
                1635336
            ],
            [
                1.116e-05,
                955926
            ],
            [
                1.117e-05,
                447903
            ],
            [
                1.118e-05,
                430749
            ],
            [
                1.119e-05,
                510246
            ],
            [
                1.12e-05,
                601426
            ],
            [
                1.121e-05,
                2335329
            ],
            [
                1.122e-05,
                722780
            ],
            [
                1.123e-05,
                483012
            ],
            [
                1.124e-05,
                592805
            ],
            [
                1.125e-05,
                608973
            ],
            [
                1.126e-05,
                476802
            ],
            [
                1.127e-05,
                480175
            ],
            [
                1.128e-05,
                642552
            ],
            [
                1.129e-05,
                824434
            ],
            [
                1.13e-05,
                784814
            ],
            [
                1.131e-05,
                361765
            ],
            [
                1.132e-05,
                800561
            ],
            [
                1.133e-05,
                187557
            ],
            [
                1.134e-05,
                360362
            ],
            [
                1.135e-05,
                1220111
            ],
            [
                1.136e-05,
                1036052
            ],
            [
                1.137e-05,
                640418
            ],
            [
                1.138e-05,
                1146485
            ],
            [
                1.139e-05,
                542419
            ]
        ],
        "bids": [
            [
                1.114e-05,
                64510
            ],
            [
                1.113e-05,
                269287
            ],
            [
                1.112e-05,
                949054
            ],
            [
                1.111e-05,
                1142638
            ],
            [
                1.11e-05,
                630563
            ],
            [
                1.109e-05,
                805861
            ],
            [
                1.108e-05,
                334593
            ],
            [
                1.107e-05,
                843165
            ],
            [
                1.106e-05,
                1560220
            ],
            [
                1.105e-05,
                547883
            ],
            [
                1.104e-05,
                407761
            ],
            [
                1.103e-05,
                353729
            ],
            [
                1.102e-05,
                214935
            ],
            [
                1.101e-05,
                164309
            ],
            [
                1.1e-05,
                910090
            ],
            [
                1.099e-05,
                353154
            ],
            [
                1.098e-05,
                120616
            ],
            [
                1.097e-05,
                371945
            ],
            [
                1.096e-05,
                188807
            ],
            [
                1.095e-05,
                249482
            ],
            [
                1.094e-05,
                358396
            ],
            [
                1.093e-05,
                298499
            ],
            [
                1.092e-05,
                262648
            ],
            [
                1.091e-05,
                2030910
            ],
            [
                1.09e-05,
                314208
            ]
        ]
    },
    "EOSH19": {
        "asks": [
            [
                0.0009238,
                17033
            ],
            [
                0.0009239,
                300
            ],
            [
                0.000924,
                9
            ],
            [
                0.0009241,
                10
            ],
            [
                0.0009243,
                182
            ],
            [
                0.0009245,
                847
            ],
            [
                0.0009246,
                17224
            ],
            [
                0.0009247,
                2632
            ],
            [
                0.0009248,
                4200
            ],
            [
                0.0009249,
                14
            ],
            [
                0.000925,
                150
            ],
            [
                0.0009251,
                4000
            ],
            [
                0.0009252,
                711
            ],
            [
                0.0009253,
                9845
            ],
            [
                0.0009255,
                214
            ],
            [
                0.0009256,
                163
            ],
            [
                0.0009258,
                16
            ],
            [
                0.0009259,
                828
            ],
            [
                0.0009261,
                1024
            ],
            [
                0.0009263,
                1500
            ],
            [
                0.0009264,
                2141
            ],
            [
                0.0009265,
                3088
            ],
            [
                0.0009266,
                13
            ],
            [
                0.0009267,
                2446
            ],
            [
                0.000927,
                197
            ]
        ],
        "bids": [
            [
                0.0009237,
                3036
            ],
            [
                0.0009236,
                200
            ],
            [
                0.0009235,
                1505
            ],
            [
                0.0009234,
                2203
            ],
            [
                0.0009231,
                216
            ],
            [
                0.000923,
                655
            ],
            [
                0.0009228,
                463
            ],
            [
                0.0009227,
                30
            ],
            [
                0.0009226,
                1050
            ],
            [
                0.0009225,
                4179
            ],
            [
                0.0009224,
                50
            ],
            [
                0.0009222,
                2071
            ],
            [
                0.0009221,
                601
            ],
            [
                0.000922,
                511
            ],
            [
                0.0009219,
                14
            ],
            [
                0.0009218,
                50
            ],
            [
                0.0009217,
                1320
            ],
            [
                0.0009216,
                366
            ],
            [
                0.0009215,
                2465
            ],
            [
                0.0009214,
                18125
            ],
            [
                0.0009213,
                18
            ],
            [
                0.0009212,
                9594
            ],
            [
                0.0009211,
                723
            ],
            [
                0.000921,
                1181
            ],
            [
                0.0009208,
                50
            ]
        ]
    },
    "TRXH19": {
        "asks": [
            [
                5.94e-06,
                2459625
            ],
            [
                5.95e-06,
                2671521
            ],
            [
                5.96e-06,
                2970412
            ],
            [
                5.97e-06,
                1791094
            ],
            [
                5.98e-06,
                1615553
            ],
            [
                5.99e-06,
                1233438
            ],
            [
                6e-06,
                1511462
            ],
            [
                6.01e-06,
                2356236
            ],
            [
                6.02e-06,
                2659324
            ],
            [
                6.03e-06,
                721050
            ],
            [
                6.04e-06,
                4031926
            ],
            [
                6.05e-06,
                4671820
            ],
            [
                6.06e-06,
                925450
            ],
            [
                6.07e-06,
                2067636
            ],
            [
                6.08e-06,
                349744
            ],
            [
                6.09e-06,
                3525764
            ],
            [
                6.1e-06,
                4614004
            ],
            [
                6.11e-06,
                3353433
            ],
            [
                6.12e-06,
                629421
            ],
            [
                6.13e-06,
                1150413
            ],
            [
                6.14e-06,
                1302094
            ],
            [
                6.15e-06,
                8166168
            ],
            [
                6.16e-06,
                2310121
            ],
            [
                6.17e-06,
                286030
            ],
            [
                6.18e-06,
                104143
            ]
        ],
        "bids": [
            [
                5.93e-06,
                2369391
            ],
            [
                5.92e-06,
                3337269
            ],
            [
                5.91e-06,
                3772289
            ],
            [
                5.9e-06,
                2884698
            ],
            [
                5.89e-06,
                1915685
            ],
            [
                5.88e-06,
                3613986
            ],
            [
                5.87e-06,
                2229280
            ],
            [
                5.86e-06,
                966227
            ],
            [
                5.85e-06,
                1866407
            ],
            [
                5.84e-06,
                1035383
            ],
            [
                5.83e-06,
                1617396
            ],
            [
                5.82e-06,
                1555012
            ],
            [
                5.81e-06,
                4698195
            ],
            [
                5.8e-06,
                3699473
            ],
            [
                5.79e-06,
                264120
            ],
            [
                5.78e-06,
                1360212
            ],
            [
                5.77e-06,
                3125465
            ],
            [
                5.76e-06,
                3728274
            ],
            [
                5.75e-06,
                3120709
            ],
            [
                5.74e-06,
                759180
            ],
            [
                5.73e-06,
                1828441
            ],
            [
                5.72e-06,
                690815
            ],
            [
                5.71e-06,
                319764
            ],
            [
                5.7e-06,
                3639066
            ],
            [
                5.69e-06,
                120623
            ]
        ]
    },
    ".XBT": {
        "asks": [],
        "bids": []
    },
    ".XBT30M": {
        "asks": [],
        "bids": []
    },
    ".XBTBON": {
        "asks": [],
        "bids": []
    },
    ".XBTBON8H": {
        "asks": [],
        "bids": []
    },
    ".XBTUSDPI": {
        "asks": [],
        "bids": []
    },
    ".XBTUSDPI8H": {
        "asks": [],
        "bids": []
    },
    ".XBTBON2H": {
        "asks": [],
        "bids": []
    },
    ".XBTUSDPI2H": {
        "asks": [],
        "bids": []
    },
    ".BXBT": {
        "asks": [],
        "bids": []
    },
    ".BXBT30M": {
        "asks": [],
        "bids": []
    },
    ".XBTJPY": {
        "asks": [],
        "bids": []
    },
    ".XBTJPY30M": {
        "asks": [],
        "bids": []
    },
    ".BXBTJPY": {
        "asks": [],
        "bids": []
    },
    ".BXBTJPY30M": {
        "asks": [],
        "bids": []
    },
    ".BVOL": {
        "asks": [],
        "bids": []
    },
    ".BVOL24H": {
        "asks": [],
        "bids": []
    },
    ".BVOL7D": {
        "asks": [],
        "bids": []
    },
    ".ETHBON": {
        "asks": [],
        "bids": []
    },
    ".ETHBON2H": {
        "asks": [],
        "bids": []
    },
    ".ETHBON8H": {
        "asks": [],
        "bids": []
    },
    ".ETHUSDPI": {
        "asks": [],
        "bids": []
    },
    ".ETHUSDPI2H": {
        "asks": [],
        "bids": []
    },
    ".ETHUSDPI8H": {
        "asks": [],
        "bids": []
    },
    ".BETH": {
        "asks": [],
        "bids": []
    },
    ".BETH30M": {
        "asks": [],
        "bids": []
    },
    ".BETHXBT": {
        "asks": [],
        "bids": []
    },
    ".BETHXBT30M": {
        "asks": [],
        "bids": []
    },
    ".BLTCXBT": {
        "asks": [],
        "bids": []
    },
    ".BLTCXBT30M": {
        "asks": [],
        "bids": []
    },
    ".USDBON": {
        "asks": [],
        "bids": []
    },
    ".USDBON8H": {
        "asks": [],
        "bids": []
    },
    ".USDBON2H": {
        "asks": [],
        "bids": []
    },
    "BTC/USD": {
        "asks": [
            [
                3801,
                1448060
            ],
            [
                3801.5,
                89861
            ],
            [
                3802,
                187984
            ],
            [
                3802.5,
                126589
            ],
            [
                3803,
                529583
            ],
            [
                3803.5,
                258636
            ],
            [
                3804,
                243477
            ],
            [
                3804.5,
                998823
            ],
            [
                3805,
                710240
            ],
            [
                3805.5,
                510026
            ],
            [
                3806,
                723284
            ],
            [
                3806.5,
                201901
            ],
            [
                3807,
                228627
            ],
            [
                3807.5,
                340105
            ],
            [
                3808,
                661579
            ],
            [
                3808.5,
                337597
            ],
            [
                3809,
                395795
            ],
            [
                3809.5,
                182899
            ],
            [
                3810,
                1009559
            ],
            [
                3810.5,
                170249
            ],
            [
                3811,
                716813
            ],
            [
                3811.5,
                251795
            ],
            [
                3812,
                419557
            ],
            [
                3812.5,
                148550
            ],
            [
                3813,
                321076
            ]
        ],
        "bids": [
            [
                3800.5,
                482309
            ],
            [
                3800,
                86604
            ],
            [
                3799.5,
                147723
            ],
            [
                3799,
                52469
            ],
            [
                3798.5,
                269604
            ],
            [
                3798,
                77244
            ],
            [
                3797.5,
                103632
            ],
            [
                3797,
                567858
            ],
            [
                3796.5,
                152674
            ],
            [
                3796,
                214895
            ],
            [
                3795.5,
                157323
            ],
            [
                3795,
                124535
            ],
            [
                3794.5,
                58730
            ],
            [
                3794,
                57547
            ],
            [
                3793.5,
                127658
            ],
            [
                3793,
                135764
            ],
            [
                3792.5,
                335909
            ],
            [
                3792,
                88140
            ],
            [
                3791.5,
                96899
            ],
            [
                3791,
                205988
            ],
            [
                3790.5,
                121831
            ],
            [
                3790,
                980961
            ],
            [
                3789.5,
                94028
            ],
            [
                3789,
                243998
            ],
            [
                3788.5,
                205789
            ]
        ]
    },
    "XBT7D_U105": {
        "asks": [
            [
                0.00406,
                9
            ],
            [
                0.00431,
                39
            ],
            [
                0.00456,
                65
            ],
            [
                0.00481,
                92
            ],
            [
                0.00506,
                119
            ]
        ],
        "bids": [
            [
                0.00355,
                2
            ],
            [
                0.0033,
                14
            ],
            [
                0.00305,
                40
            ],
            [
                0.0028,
                67
            ],
            [
                0.0027,
                3
            ],
            [
                0.00255,
                94
            ],
            [
                0.0023,
                1
            ],
            [
                9e-05,
                5
            ],
            [
                1e-05,
                10
            ]
        ]
    },
    "XBT7D_D95": {
        "asks": [
            [
                0.00305,
                18
            ],
            [
                0.0033,
                56
            ],
            [
                0.00355,
                83
            ],
            [
                0.0038,
                110
            ],
            [
                0.00405,
                136
            ]
        ],
        "bids": [
            [
                0.00254,
                11
            ],
            [
                0.00229,
                3
            ],
            [
                0.00204,
                23
            ],
            [
                0.00179,
                49
            ],
            [
                0.00154,
                76
            ],
            [
                0.00025,
                10
            ],
            [
                0.0001,
                100
            ],
            [
                2e-05,
                10
            ],
            [
                1e-05,
                60
            ]
        ]
    },
    "XBTH19": {
        "asks": [
            [
                3792.5,
                45792
            ],
            [
                3793,
                46473
            ],
            [
                3793.5,
                37393
            ],
            [
                3794,
                1010
            ],
            [
                3795,
                3193
            ],
            [
                3796,
                45636
            ],
            [
                3796.5,
                3784
            ],
            [
                3797,
                13240
            ],
            [
                3797.5,
                6100
            ],
            [
                3798,
                2000
            ],
            [
                3798.5,
                23147
            ],
            [
                3799,
                43450
            ],
            [
                3799.5,
                14010
            ],
            [
                3800,
                47858
            ],
            [
                3800.5,
                2574
            ],
            [
                3801,
                2228
            ],
            [
                3801.5,
                4208
            ],
            [
                3802,
                4630
            ],
            [
                3802.5,
                53962
            ],
            [
                3803,
                9666
            ],
            [
                3803.5,
                410
            ],
            [
                3804,
                8100
            ],
            [
                3804.5,
                85520
            ],
            [
                3805,
                41950
            ],
            [
                3805.5,
                1000
            ]
        ],
        "bids": [
            [
                3792,
                64917
            ],
            [
                3791.5,
                11493
            ],
            [
                3791,
                47275
            ],
            [
                3790,
                15142
            ],
            [
                3789.5,
                5702
            ],
            [
                3789,
                20
            ],
            [
                3788.5,
                5000
            ],
            [
                3788,
                7530
            ],
            [
                3787.5,
                5000
            ],
            [
                3787,
                13858
            ],
            [
                3786,
                55675
            ],
            [
                3785.5,
                50527
            ],
            [
                3785,
                2500
            ],
            [
                3784.5,
                3028
            ],
            [
                3784,
                22
            ],
            [
                3783.5,
                5350
            ],
            [
                3783,
                52999
            ],
            [
                3782.5,
                9000
            ],
            [
                3782,
                7515
            ],
            [
                3781.5,
                44
            ],
            [
                3781,
                49589
            ],
            [
                3780.5,
                1500
            ],
            [
                3780,
                46361
            ],
            [
                3779.5,
                377
            ],
            [
                3779,
                20000
            ]
        ]
    },
    "XBTM19": {
        "asks": [
            [
                3773,
                28068
            ],
            [
                3773.5,
                12376
            ],
            [
                3774,
                6160
            ],
            [
                3774.5,
                3774
            ],
            [
                3775,
                6296
            ],
            [
                3775.5,
                573
            ],
            [
                3776,
                6577
            ],
            [
                3776.5,
                50626
            ],
            [
                3777,
                45213
            ],
            [
                3777.5,
                2250
            ],
            [
                3778,
                1250
            ],
            [
                3778.5,
                37467
            ],
            [
                3779,
                1260
            ],
            [
                3779.5,
                12799
            ],
            [
                3780,
                7351
            ],
            [
                3781,
                660
            ],
            [
                3781.5,
                14000
            ],
            [
                3782,
                1750
            ],
            [
                3782.5,
                3473
            ],
            [
                3783,
                7560
            ],
            [
                3783.5,
                536
            ],
            [
                3784,
                19150
            ],
            [
                3785,
                9840
            ],
            [
                3785.5,
                17000
            ],
            [
                3786,
                10154
            ]
        ],
        "bids": [
            [
                3772.5,
                86442
            ],
            [
                3772,
                5010
            ],
            [
                3771.5,
                20188
            ],
            [
                3771,
                4050
            ],
            [
                3770.5,
                270
            ],
            [
                3770,
                14525
            ],
            [
                3769.5,
                57999
            ],
            [
                3769,
                708
            ],
            [
                3768,
                40
            ],
            [
                3767.5,
                628
            ],
            [
                3767,
                8700
            ],
            [
                3766.5,
                10500
            ],
            [
                3766,
                44922
            ],
            [
                3765.5,
                26
            ],
            [
                3765,
                2947
            ],
            [
                3764.5,
                5908
            ],
            [
                3764,
                305
            ],
            [
                3763.5,
                5109
            ],
            [
                3763,
                450
            ],
            [
                3762.5,
                3501
            ],
            [
                3762,
                5697
            ],
            [
                3761.5,
                10822
            ],
            [
                3761,
                2229
            ],
            [
                3760.5,
                15300
            ],
            [
                3760,
                1200
            ]
        ]
    },
    "ETH/USD": {
        "asks": [
            [
                129.7,
                161132
            ],
            [
                129.75,
                448346
            ],
            [
                129.8,
                302668
            ],
            [
                129.85,
                112701
            ],
            [
                129.9,
                426575
            ],
            [
                129.95,
                201806
            ],
            [
                130,
                111102
            ],
            [
                130.05,
                76805
            ],
            [
                130.1,
                189537
            ],
            [
                130.15,
                106092
            ],
            [
                130.2,
                162207
            ],
            [
                130.25,
                538276
            ],
            [
                130.3,
                295136
            ],
            [
                130.35,
                29301
            ],
            [
                130.4,
                466480
            ],
            [
                130.45,
                187564
            ],
            [
                130.5,
                473633
            ],
            [
                130.55,
                23753
            ],
            [
                130.6,
                268264
            ],
            [
                130.65,
                157499
            ],
            [
                130.7,
                295677
            ],
            [
                130.75,
                91690
            ],
            [
                130.8,
                313892
            ],
            [
                130.85,
                224675
            ],
            [
                130.9,
                495797
            ]
        ],
        "bids": [
            [
                129.65,
                525739
            ],
            [
                129.6,
                343724
            ],
            [
                129.55,
                272192
            ],
            [
                129.5,
                64099
            ],
            [
                129.45,
                226996
            ],
            [
                129.4,
                1114384
            ],
            [
                129.35,
                346664
            ],
            [
                129.3,
                331400
            ],
            [
                129.25,
                101476
            ],
            [
                129.2,
                66448
            ],
            [
                129.15,
                127687
            ],
            [
                129.1,
                48459
            ],
            [
                129.05,
                78839
            ],
            [
                129,
                682360
            ],
            [
                128.95,
                15749
            ],
            [
                128.9,
                31083
            ],
            [
                128.85,
                32833
            ],
            [
                128.8,
                38276
            ],
            [
                128.75,
                209912
            ],
            [
                128.7,
                233869
            ],
            [
                128.65,
                201136
            ],
            [
                128.6,
                41179
            ],
            [
                128.55,
                98030
            ],
            [
                128.5,
                498178
            ],
            [
                128.45,
                186871
            ]
        ]
    },
    "ETHH19": {
        "asks": [
            [
                0.03415,
                353
            ],
            [
                0.03416,
                34
            ],
            [
                0.03417,
                413
            ],
            [
                0.03418,
                59
            ],
            [
                0.03419,
                80
            ],
            [
                0.0342,
                70
            ],
            [
                0.03421,
                101
            ],
            [
                0.03422,
                643
            ],
            [
                0.03423,
                142
            ],
            [
                0.03424,
                67
            ],
            [
                0.03425,
                353
            ],
            [
                0.03426,
                13
            ],
            [
                0.03427,
                8
            ],
            [
                0.03428,
                15
            ],
            [
                0.03429,
                21
            ],
            [
                0.0343,
                1
            ],
            [
                0.03431,
                26
            ],
            [
                0.03432,
                38
            ],
            [
                0.03433,
                144
            ],
            [
                0.03434,
                853
            ],
            [
                0.03435,
                194
            ],
            [
                0.03436,
                60
            ],
            [
                0.03438,
                14
            ],
            [
                0.03439,
                98
            ],
            [
                0.03442,
                55
            ]
        ],
        "bids": [
            [
                0.03414,
                255
            ],
            [
                0.03413,
                294
            ],
            [
                0.03412,
                116
            ],
            [
                0.03411,
                56
            ],
            [
                0.03409,
                399
            ],
            [
                0.03408,
                317
            ],
            [
                0.03407,
                20
            ],
            [
                0.03406,
                422
            ],
            [
                0.03405,
                118
            ],
            [
                0.03404,
                27
            ],
            [
                0.03403,
                1
            ],
            [
                0.03402,
                12
            ],
            [
                0.03401,
                153
            ],
            [
                0.034,
                56
            ],
            [
                0.03399,
                8
            ],
            [
                0.03398,
                17
            ],
            [
                0.03397,
                2
            ],
            [
                0.03396,
                13
            ],
            [
                0.03395,
                51
            ],
            [
                0.03394,
                154
            ],
            [
                0.03393,
                109
            ],
            [
                0.03392,
                129
            ],
            [
                0.03391,
                16
            ],
            [
                0.0339,
                13
            ],
            [
                0.03389,
                45
            ]
        ]
    },
    "LTCH19": {
        "asks": [
            [
                0.01247,
                755
            ],
            [
                0.01248,
                601
            ],
            [
                0.01249,
                1135
            ],
            [
                0.0125,
                1311
            ],
            [
                0.01251,
                922
            ],
            [
                0.01252,
                3289
            ],
            [
                0.01253,
                740
            ],
            [
                0.01254,
                816
            ],
            [
                0.01255,
                3444
            ],
            [
                0.01256,
                3176
            ],
            [
                0.01257,
                1765
            ],
            [
                0.01258,
                941
            ],
            [
                0.01259,
                3416
            ],
            [
                0.0126,
                2922
            ],
            [
                0.01261,
                1234
            ],
            [
                0.01262,
                1182
            ],
            [
                0.01263,
                303
            ],
            [
                0.01264,
                2175
            ],
            [
                0.01265,
                1979
            ],
            [
                0.01266,
                696
            ],
            [
                0.01267,
                1083
            ],
            [
                0.01268,
                2177
            ],
            [
                0.01269,
                503
            ],
            [
                0.0127,
                3501
            ],
            [
                0.01271,
                717
            ]
        ],
        "bids": [
            [
                0.01246,
                1680
            ],
            [
                0.01245,
                668
            ],
            [
                0.01244,
                604
            ],
            [
                0.01243,
                359
            ],
            [
                0.01242,
                503
            ],
            [
                0.01241,
                433
            ],
            [
                0.0124,
                459
            ],
            [
                0.01239,
                2531
            ],
            [
                0.01238,
                2542
            ],
            [
                0.01237,
                2380
            ],
            [
                0.01236,
                3346
            ],
            [
                0.01235,
                808
            ],
            [
                0.01234,
                637
            ],
            [
                0.01233,
                1142
            ],
            [
                0.01232,
                739
            ],
            [
                0.01231,
                1097
            ],
            [
                0.0123,
                2850
            ],
            [
                0.01229,
                3418
            ],
            [
                0.01228,
                2657
            ],
            [
                0.01227,
                3117
            ],
            [
                0.01226,
                12194
            ],
            [
                0.01225,
                2461
            ],
            [
                0.01224,
                1038
            ],
            [
                0.01223,
                150
            ],
            [
                0.01222,
                4445
            ]
        ]
    }
}